bqsensorgen/__init__.py
bqsensorgen/sensorgen.py
bqsensorgen-0.0.1.dist-info/LICENSE
bqsensorgen-0.0.1.dist-info/METADATA
bqsensorgen-0.0.1.dist-info/WHEEL
bqsensorgen-0.0.1.dist-info/top_level.txt
bqsensorgen-0.0.1.dist-info/RECORD
