Metadata-Version: 2.1
Name: bqsensorgen
Version: 0.0.1
Summary: Generate sensor queries from your BigQuery queries.
Author-email: Iúry Pinto <iurysp@hotmail.com>
License: The MIT License (MIT)
Keywords: sensor,sql,query,bigquery,bq
Classifier: License :: OSI Approved :: MIT License
Classifier: Programming Language :: Python
Classifier: Programming Language :: Python :: 3
Classifier: Programming Language :: Python :: 3 :: Only
Classifier: Programming Language :: Python :: 3.7
Classifier: Programming Language :: Python :: 3.8
Classifier: Programming Language :: Python :: 3.9
Classifier: Programming Language :: Python :: 3.10
Requires-Python: >=3
License-File: LICENSE
